<?xml version="1.0" ?>
<trendmodel>
  <class>polytrend</class>
  <config>
    <avg_trend>
      <ref_level>50.</ref_level>
      <x_lo>0.0</x_lo>
      <x_hi>1.0</x_hi>
    </avg_trend>
    <std_trend>
      <ref_level>20.</ref_level>
      <x_lo>0.0</x_lo>
      <x_hi>100.0</x_hi>
    </std_trend>
  </config>
  <start_date>2008-01-01</start_date>
  <end_date>2012-12-31</end_date>
  <trend>
    <week>
      <da>
        <avg>7.173033 -31.765547 53.915416</avg>
        <std>-2.153020 21.337689</std>
        <avg_err>7.625373 -16.141062 12.712427 -4.445655 4.681198</avg_err>
        <std_err>0.294266 -0.323042 1.630807</std_err>
      </da>
    </week>
    <weekend>
      <da>
        <avg>6.201995 -24.709129 56.576362</avg>
        <std>1.258224 18.454839</std>
        <avg_err>6.934242 -14.678105 11.560227 -4.042720 4.256914</avg_err>
        <std_err>0.244009 -0.267871 1.352288</std_err>
      </da>
    </weekend>
  </trend>
  <stat_param>
    <station name="41B004">
      <week>
        <da>
          <avg>32.093548</avg>
          <std>19.901232</std>
        </da>
      </week>
      <weekend>
        <da>
          <avg>38.371486</avg>
          <std>20.179490</std>
        </da>
      </weekend>
    </station>
    <station name="41B006">
      <week>
        <da>
          <avg>37.068673</avg>
          <std>21.618648</std>
        </da>
      </week>
      <weekend>
        <da>
          <avg>45.781609</avg>
          <std>21.529478</std>
        </da>
      </weekend>
    </station>
    <station name="41B011">
      <week>
        <da>
          <avg>37.853261</avg>
          <std>21.313862</std>
        </da>
      </week>
      <weekend>
        <da>
          <avg>45.094412</avg>
          <std>20.638101</std>
        </da>
      </weekend>
    </station>
    <station name="41N043">
      <week>
        <da>
          <avg>25.376643</avg>
          <std>16.733792</std>
        </da>
      </week>
      <weekend>
        <da>
          <avg>35.818882</avg>
          <std>18.420285</std>
        </da>
      </weekend>
    </station>
    <station name="41R001">
      <week>
        <da>
          <avg>32.171053</avg>
          <std>18.988586</std>
        </da>
      </week>
      <weekend>
        <da>
          <avg>39.528736</avg>
          <std>19.165211</std>
        </da>
      </weekend>
    </station>
    <station name="41R012">
      <week>
        <da>
          <avg>42.968266</avg>
          <std>22.375738</std>
        </da>
      </week>
      <weekend>
        <da>
          <avg>49.479846</avg>
          <std>21.228973</std>
        </da>
      </weekend>
    </station>
    <station name="41WOL1">
      <week>
        <da>
          <avg>30.397013</avg>
          <std>18.802475</std>
        </da>
      </week>
      <weekend>
        <da>
          <avg>37.850980</avg>
          <std>19.427700</std>
        </da>
      </weekend>
    </station>
    <station name="42N016">
      <week>
        <da>
          <avg>39.000000</avg>
          <std>22.291783</std>
        </da>
      </week>
      <weekend>
        <da>
          <avg>45.061475</avg>
          <std>20.849621</std>
        </da>
      </weekend>
    </station>
    <station name="42N027">
      <week>
        <da>
          <avg>40.262118</avg>
          <std>21.835320</std>
        </da>
      </week>
      <weekend>
        <da>
          <avg>45.958810</avg>
          <std>20.127874</std>
        </da>
      </weekend>
    </station>
    <station name="42N035">
      <week>
        <da>
          <avg>41.994382</avg>
          <std>22.839179</std>
        </da>
      </week>
      <weekend>
        <da>
          <avg>48.757637</avg>
          <std>21.118043</std>
        </da>
      </weekend>
    </station>
    <station name="42N040">
      <week>
        <da>
          <avg>42.675523</avg>
          <std>20.620750</std>
        </da>
      </week>
      <weekend>
        <da>
          <avg>48.371134</avg>
          <std>19.081664</std>
        </da>
      </weekend>
    </station>
    <station name="42N045">
      <week>
        <da>
          <avg>39.600328</avg>
          <std>21.758303</std>
        </da>
      </week>
      <weekend>
        <da>
          <avg>47.154506</avg>
          <std>20.827137</std>
        </da>
      </weekend>
    </station>
    <station name="42N046">
      <week>
        <da>
          <avg>39.945661</avg>
          <std>20.903872</std>
        </da>
      </week>
      <weekend>
        <da>
          <avg>45.847599</avg>
          <std>19.669756</std>
        </da>
      </weekend>
    </station>
    <station name="42N054">
      <week>
        <da>
          <avg>42.390185</avg>
          <std>21.234443</std>
        </da>
      </week>
      <weekend>
        <da>
          <avg>48.336777</avg>
          <std>18.959808</std>
        </da>
      </weekend>
    </station>
    <station name="42R801">
      <week>
        <da>
          <avg>27.257576</avg>
          <std>18.704955</std>
        </da>
      </week>
      <weekend>
        <da>
          <avg>36.081633</avg>
          <std>19.977940</std>
        </da>
      </weekend>
    </station>
    <station name="42R811">
      <week>
        <da>
          <avg>34.578275</avg>
          <std>20.671179</std>
        </da>
      </week>
      <weekend>
        <da>
          <avg>43.256619</avg>
          <std>20.237451</std>
        </da>
      </weekend>
    </station>
    <station name="42R831">
      <week>
        <da>
          <avg>31.621249</avg>
          <std>19.687620</std>
        </da>
      </week>
      <weekend>
        <da>
          <avg>38.915114</avg>
          <std>19.400856</std>
        </da>
      </weekend>
    </station>
    <station name="42R841">
      <week>
        <da>
          <avg>31.118314</avg>
          <std>18.950927</std>
        </da>
      </week>
      <weekend>
        <da>
          <avg>41.076763</avg>
          <std>19.329303</std>
        </da>
      </weekend>
    </station>
    <station name="43N060">
      <week>
        <da>
          <avg>36.455556</avg>
          <std>17.423559</std>
        </da>
      </week>
      <weekend>
        <da>
          <avg>40.584699</avg>
          <std>17.695600</std>
        </da>
      </weekend>
    </station>
    <station name="43N063">
      <week>
        <da>
          <avg>41.892549</avg>
          <std>20.304709</std>
        </da>
      </week>
      <weekend>
        <da>
          <avg>46.607767</avg>
          <std>18.383653</std>
        </da>
      </weekend>
    </station>
    <station name="43N066">
      <week>
        <da>
          <avg>48.587127</avg>
          <std>22.320750</std>
        </da>
      </week>
      <weekend>
        <da>
          <avg>53.351563</avg>
          <std>19.449906</std>
        </da>
      </weekend>
    </station>
    <station name="43N070">
      <week>
        <da>
          <avg>29.508222</avg>
          <std>17.400347</std>
        </da>
      </week>
      <weekend>
        <da>
          <avg>35.343629</avg>
          <std>17.420770</std>
        </da>
      </weekend>
    </station>
    <station name="43N073">
      <week>
        <da>
          <avg>41.000784</avg>
          <std>19.464273</std>
        </da>
      </week>
      <weekend>
        <da>
          <avg>44.932039</avg>
          <std>17.359140</std>
        </da>
      </weekend>
    </station>
    <station name="43N085">
      <week>
        <da>
          <avg>46.527059</avg>
          <std>19.822046</std>
        </da>
      </week>
      <weekend>
        <da>
          <avg>49.281853</avg>
          <std>18.304160</std>
        </da>
      </weekend>
    </station>
    <station name="43N093">
      <week>
        <da>
          <avg>47.326002</avg>
          <std>19.784565</std>
        </da>
      </week>
      <weekend>
        <da>
          <avg>51.053950</avg>
          <std>17.781953</std>
        </da>
      </weekend>
    </station>
    <station name="43N100">
      <week>
        <da>
          <avg>54.043956</avg>
          <std>20.555283</std>
        </da>
      </week>
      <weekend>
        <da>
          <avg>56.938343</avg>
          <std>17.814685</std>
        </da>
      </weekend>
    </station>
    <station name="43N113">
      <week>
        <da>
          <avg>55.645719</avg>
          <std>21.104323</std>
        </da>
      </week>
      <weekend>
        <da>
          <avg>58.787645</avg>
          <std>18.794863</std>
        </da>
      </weekend>
    </station>
    <station name="43N121">
      <week>
        <da>
          <avg>52.883137</avg>
          <std>21.376192</std>
        </da>
      </week>
      <weekend>
        <da>
          <avg>56.009766</avg>
          <std>18.889055</std>
        </da>
      </weekend>
    </station>
    <station name="43N132">
      <week>
        <da>
          <avg>49.683240</avg>
          <std>22.084434</std>
        </da>
      </week>
      <weekend>
        <da>
          <avg>53.577603</avg>
          <std>19.136074</std>
        </da>
      </weekend>
    </station>
    <station name="43R201">
      <week>
        <da>
          <avg>36.358833</avg>
          <std>20.896062</std>
        </da>
      </week>
      <weekend>
        <da>
          <avg>42.560078</avg>
          <std>20.165102</std>
        </da>
      </weekend>
    </station>
    <station name="43R222">
      <week>
        <da>
          <avg>37.437344</avg>
          <std>20.567378</std>
        </da>
      </week>
      <weekend>
        <da>
          <avg>43.833333</avg>
          <std>20.061125</std>
        </da>
      </weekend>
    </station>
    <station name="43R240">
      <week>
        <da>
          <avg>40.601742</avg>
          <std>20.771885</std>
        </da>
      </week>
      <weekend>
        <da>
          <avg>44.939453</avg>
          <std>19.029955</std>
        </da>
      </weekend>
    </station>
    <station name="44M705">
      <week>
        <da>
          <avg>37.616733</avg>
          <std>19.078839</std>
        </da>
      </week>
      <weekend>
        <da>
          <avg>46.244980</avg>
          <std>18.607570</std>
        </da>
      </weekend>
    </station>
    <station name="44N012">
      <week>
        <da>
          <avg>42.072621</avg>
          <std>19.207800</std>
        </da>
      </week>
      <weekend>
        <da>
          <avg>47.334056</avg>
          <std>17.727684</std>
        </da>
      </weekend>
    </station>
    <station name="44N029">
      <week>
        <da>
          <avg>44.673307</avg>
          <std>18.421826</std>
        </da>
      </week>
      <weekend>
        <da>
          <avg>48.811623</avg>
          <std>17.254200</std>
        </da>
      </weekend>
    </station>
    <station name="44N051">
      <week>
        <da>
          <avg>40.778931</avg>
          <std>19.868573</std>
        </da>
      </week>
      <weekend>
        <da>
          <avg>45.628049</avg>
          <std>18.420464</std>
        </da>
      </weekend>
    </station>
    <station name="44N052">
      <week>
        <da>
          <avg>34.572705</avg>
          <std>18.133723</std>
        </da>
      </week>
      <weekend>
        <da>
          <avg>41.530738</avg>
          <std>17.463223</std>
        </da>
      </weekend>
    </station>
    <station name="44R701">
      <week>
        <da>
          <avg>34.430952</avg>
          <std>20.087082</std>
        </da>
      </week>
      <weekend>
        <da>
          <avg>42.101215</avg>
          <std>19.908459</std>
        </da>
      </weekend>
    </station>
    <station name="44R710">
      <week>
        <da>
          <avg>36.189752</avg>
          <std>20.063721</std>
        </da>
      </week>
      <weekend>
        <da>
          <avg>43.812371</avg>
          <std>19.376112</std>
        </da>
      </weekend>
    </station>
    <station name="44R740">
      <week>
        <da>
          <avg>34.444713</avg>
          <std>18.622427</std>
        </da>
      </week>
      <weekend>
        <da>
          <avg>42.782787</avg>
          <std>18.054161</std>
        </da>
      </weekend>
    </station>
    <station name="45R502">
      <week>
        <da>
          <avg>33.508248</avg>
          <std>19.353387</std>
        </da>
      </week>
      <weekend>
        <da>
          <avg>39.029070</avg>
          <std>18.105546</std>
        </da>
      </weekend>
    </station>
  </stat_param>
</trendmodel>
